sqlalchemy_vectorstores/__init__.py
sqlalchemy_vectorstores/databases/__init__.py
sqlalchemy_vectorstores/databases/base.py
sqlalchemy_vectorstores/databases/base_async.py
sqlalchemy_vectorstores/databases/postgres.py
sqlalchemy_vectorstores/databases/postgres_async.py
sqlalchemy_vectorstores/databases/sa_types.py
sqlalchemy_vectorstores/databases/sqlite.py
sqlalchemy_vectorstores/databases/sqlite_async.py
sqlalchemy_vectorstores/retrievers/__init__.py
sqlalchemy_vectorstores/retrievers/base.py
sqlalchemy_vectorstores/tokenizers/__init__.py
sqlalchemy_vectorstores/tokenizers/base.py
sqlalchemy_vectorstores/tokenizers/jieba_tokenize.py
sqlalchemy_vectorstores/vectorstores/__init__.py
sqlalchemy_vectorstores/vectorstores/base.py
sqlalchemy_vectorstores/vectorstores/base_async.py
sqlalchemy_vectorstores/vectorstores/postgres.py
sqlalchemy_vectorstores/vectorstores/postgres_async.py
sqlalchemy_vectorstores/vectorstores/sqlite.py
sqlalchemy_vectorstores/vectorstores/sqlite_async.py
sqlalchemy_vectorstores/vectorstores/utils.py
sqlalchemy_vectorstores-0.1.3.post1.dist-info/METADATA
sqlalchemy_vectorstores-0.1.3.post1.dist-info/WHEEL
sqlalchemy_vectorstores-0.1.3.post1.dist-info/RECORD
