Metadata-Version: 2.1
Name: sqlalchemy-vectorstores
Version: 0.1.3.post1
Summary: a vectorstore supports vector & bm25 search using sqlite or postgresql
Author: liunux4odoo
Author-email: liunux@qq.com
Requires-Python: >=3.8,<4.0
Classifier: Programming Language :: Python :: 3
Classifier: Programming Language :: Python :: 3.8
Classifier: Programming Language :: Python :: 3.9
Classifier: Programming Language :: Python :: 3.10
Classifier: Programming Language :: Python :: 3.11
Classifier: Programming Language :: Python :: 3.12
Classifier: Programming Language :: Python :: 3.13
Provides-Extra: asqlite
Provides-Extra: postgres
Provides-Extra: sqlite
Requires-Dist: sqlalchemy (>=2.0,<3.0)
Requires-Dist: sqlalchemy-utils (>=0.41.2,<0.42.0)
